{
  "projectId": "gen-lang-client-0931665726",
  "databaseURL": "https://gen-lang-client-0931665726-default-rtdb.firebaseio.com",
  "appId": "1:464585249922:web:608873f41cc37b8555109b",
  "apiKey": "AIzaSyAh18gO7mjXpQlgst84MIfQ_rQXk76n9SY",
  "authDomain": "gen-lang-client-0931665726.firebaseapp.com",
  "firestoreDatabaseId": "ai-studio-d87c4819-96e2-4d26-ab43-7871e0d3509a",
  "storageBucket": "gen-lang-client-0931665726.firebasestorage.app",
  "messagingSenderId": "464585249922",
  "measurementId": ""
}